{
  "last_updated": "2025-11-06T10:01:40.514296",
  "source": "https://ipowatch.in/ipo-grey-market-premium-latest/",
  "data": [
    {
      "ipo_name": "Orkla India",
      "gmp": "₹65",
      "price_band": "₹730",
      "listing_gain": "8.90%"
    },
    {
      "ipo_name": "Studds Accessories",
      "gmp": "₹62",
      "price_band": "₹585",
      "listing_gain": "10.59%"
    },
    {
      "ipo_name": "Lenskart Solutions",
      "gmp": "₹44",
      "price_band": "₹402",
      "listing_gain": "10.94%"
    },
    {
      "ipo_name": "Groww",
      "gmp": "₹14",
      "price_band": "₹100",
      "listing_gain": "14.00%"
    },
    {
      "ipo_name": "Pine Labs",
      "gmp": "₹18",
      "price_band": "₹221",
      "listing_gain": "8.14%"
    },
    {
      "ipo_name": "PhysicsWallah",
      "gmp": "₹9",
      "price_band": "₹109",
      "listing_gain": "8.25%"
    },
    {
      "ipo_name": "Emmvee Photovoltaic",
      "gmp": "₹20",
      "price_band": "₹217",
      "listing_gain": "9.21%"
    },
    {
      "ipo_name": "Tenneco Clean Air",
      "gmp": "₹100",
      "price_band": "₹-",
      "listing_gain": "-%"
    },
    {
      "ipo_name": "Safecure Services",
      "gmp": "₹-",
      "price_band": "₹102",
      "listing_gain": "-%"
    },
    {
      "ipo_name": "Shreeji Global FMCG",
      "gmp": "₹-",
      "price_band": "₹125",
      "listing_gain": "-%"
    },
    {
      "ipo_name": "Finbud Financial",
      "gmp": "₹-",
      "price_band": "₹142",
      "listing_gain": "-%"
    },
    {
      "ipo_name": "Curis Lifesciences",
      "gmp": "₹6",
      "price_band": "₹128",
      "listing_gain": "4.68%"
    },
    {
      "ipo_name": "Shining Tools",
      "gmp": "₹-",
      "price_band": "₹114",
      "listing_gain": "-%"
    },
    {
      "ipo_name": "Mahamaya Lifesciences",
      "gmp": "₹-",
      "price_band": "₹114",
      "listing_gain": "-%"
    },
    {
      "ipo_name": "Workmates Core2Cloud",
      "gmp": "₹-",
      "price_band": "₹204",
      "listing_gain": "-%"
    },
    {
      "ipo_name": "Shipwaves Online",
      "gmp": "₹-",
      "price_band": "₹12",
      "listing_gain": "-%"
    },
    {
      "ipo_name": "Riddhi Display",
      "gmp": "₹-",
      "price_band": "₹100",
      "listing_gain": "-%"
    }
  ]
}