{
  "last_updated": "2026-02-11T03:14:42.104833",
  "source": "https://ipowatch.in/ipo-grey-market-premium-latest/",
  "data": [
    {
      "ipo_name": "Fractal Analytics",
      "gmp": "₹7",
      "price_band": "₹900",
      "listing_gain": "0.78%"
    },
    {
      "ipo_name": "Aye Finance",
      "gmp": "₹0",
      "price_band": "₹129",
      "listing_gain": "-%"
    },
    {
      "ipo_name": "Grover Jewells",
      "gmp": "₹0",
      "price_band": "₹88",
      "listing_gain": "-%"
    },
    {
      "ipo_name": "Brandman Retail",
      "gmp": "₹17",
      "price_band": "₹176",
      "listing_gain": "9.66%"
    },
    {
      "ipo_name": "Biopol Chemicals",
      "gmp": "₹4",
      "price_band": "₹108",
      "listing_gain": "3.70%"
    },
    {
      "ipo_name": "PAN HR Solutions",
      "gmp": "₹0",
      "price_band": "₹78",
      "listing_gain": "-%"
    },
    {
      "ipo_name": "Marushika Technology",
      "gmp": "₹0",
      "price_band": "₹117",
      "listing_gain": "-%"
    },
    {
      "ipo_name": "Fractal Industries",
      "gmp": "₹0",
      "price_band": "₹216",
      "listing_gain": "-%"
    }
  ]
}